xstate/__init__.py
xstate/action.py
xstate/algorithm.py
xstate/event.py
xstate/interpreter.py
xstate/machine.py
xstate/scxml.py
xstate/state.py
xstate/state_node.py
xstate/transition.py
xstate-0.0.1.dist-info/LICENSE
xstate-0.0.1.dist-info/METADATA
xstate-0.0.1.dist-info/WHEEL
xstate-0.0.1.dist-info/top_level.txt
xstate-0.0.1.dist-info/RECORD
