Metadata-Version: 2.1
Name: xstate
Version: 0.0.1
Summary: XState for Python
Home-page: https://github.com/davidkpiano/xstate-python
Author: David Khourshid
Author-email: davidkpiano@gmail.com
License: MIT
Keywords: Answer Set Programming,wrapper,clingo
Platform: UNKNOWN
Classifier: License :: OSI Approved :: MIT License
Classifier: Programming Language :: Python :: 3
Classifier: Programming Language :: Python :: 3.7
Requires-Dist: ipython (>=6)
Requires-Dist: nbformat (>=4)
Requires-Dist: nbconvert (>=5)
Requires-Dist: requests (>=2)
